roi_tanh/__init__.py
roi_tanh/tanh_warper.py
roi_tanh/utils/__init__.py
roi_tanh/utils/clear.py
roi_tanh/utils/getlogger.py
roi_tanh/utils/packages.py
roi_tanh/utils/test.py
roi_tanh/warping/__init__.py
roi_tanh/warping/fastwarping.py
roi_tanh/warping/grid_sampler.py
roi_tanh/warping/warping.py
roi_tanh_tensorflow-0.0.4.dist-info/METADATA
roi_tanh_tensorflow-0.0.4.dist-info/WHEEL
roi_tanh_tensorflow-0.0.4.dist-info/top_level.txt
roi_tanh_tensorflow-0.0.4.dist-info/RECORD
