Metadata-Version: 2.1
Name: roi_tanh_tensorflow
Version: 0.0.4
Summary: apply roi tanh warping in tensorflow for face parsing
Author-email: Edouard Yvinec <ey@datakalab.com>
Project-URL: documentation, https://openaccess.thecvf.com/content_CVPR_2019/papers/Lin_Face_Parsing_With_RoI_Tanh-Warping_CVPR_2019_paper.pdf
Classifier: Programming Language :: Python :: 3
Requires-Python: >=3.9
